backoff/__init__.py
backoff/py.typed
envoy/extensions/filters/http/grpc_json_transcoder/v3/transcoder_pb2.py
google/api/annotations_pb2.py
google/api/field_behavior_pb2.py
google/api/http_pb2.py
google/api/httpbody_pb2.py
google/rpc/error_details_pb2.py
kubernetes_utils/api.py
kubernetes_utils/custom_object.py
kubernetes_utils/helpers.py
kubernetes_utils/kubernetes_client.py
kubernetes_utils/ownership.py
kubernetes_utils/retry.py
kubernetes_utils/resources/cluster_role_bindings.py
kubernetes_utils/resources/cluster_roles.py
kubernetes_utils/resources/custom_objects.py
kubernetes_utils/resources/custom_resource_definitions.py
kubernetes_utils/resources/deployments.py
kubernetes_utils/resources/namespaces.py
kubernetes_utils/resources/nodes.py
kubernetes_utils/resources/persistent_volume_claims.py
kubernetes_utils/resources/pods.py
kubernetes_utils/resources/role_bindings.py
kubernetes_utils/resources/roles.py
kubernetes_utils/resources/secrets.py
kubernetes_utils/resources/service_accounts.py
kubernetes_utils/resources/services.py
kubernetes_utils/resources/storage_classes.py
pyprotoc_plugin/__init__.py
pyprotoc_plugin/helpers.py
pyprotoc_plugin/plugins.py
resemble/cluster_setup.py
resemble/helpers.py
resemble/naming.py
resemble/options.py
resemble/protoc-gen-es_with_deps
resemble/protoc-gen-mypy
resemble/protoc-gen-resemble_nodejs
resemble/protoc-gen-resemble_nodejs_boilerplate
resemble/protoc-gen-resemble_python
resemble/protoc-gen-resemble_python_boilerplate
resemble/protoc-gen-resemble_react
resemble/protoc_gen_es_with_deps.cjs
resemble/protoc_gen_es_with_deps.py
resemble/protoc_gen_mypy_wrapper.py
resemble/protoc_gen_resemble_generic.py
resemble/protoc_gen_resemble_nodejs.py
resemble/protoc_gen_resemble_nodejs_boilerplate.py
resemble/protoc_gen_resemble_python.py
resemble/protoc_gen_resemble_python_boilerplate.py
resemble/protoc_gen_resemble_react.py
resemble/protoc_gen_resemble_typescript.py
resemble/py.typed
resemble/run_environments.py
resemble/settings.py
reboot_resemble-0.13.2.dist-info/LICENSE
reboot_resemble-0.13.2.dist-info/METADATA
reboot_resemble-0.13.2.dist-info/WHEEL
reboot_resemble-0.13.2.dist-info/entry_points.txt
reboot_resemble-0.13.2.dist-info/top_level.txt
reboot_resemble-0.13.2.dist-info/RECORD
